netman/__init__.py
netman/main.py
netman/adapters/__init__.py
netman/adapters/memory_session_storage.py
netman/adapters/memory_storage.py
netman/adapters/threading_lock_factory.py
netman/adapters/shell/__init__.py
netman/adapters/shell/base.py
netman/adapters/shell/ssh.py
netman/adapters/shell/telnet.py
netman/adapters/switches/__init__.py
netman/adapters/switches/arista.py
netman/adapters/switches/brocade.py
netman/adapters/switches/cached.py
netman/adapters/switches/cisco.py
netman/adapters/switches/dell.py
netman/adapters/switches/dell10g.py
netman/adapters/switches/remote.py
netman/adapters/switches/util.py
netman/adapters/switches/juniper/__init__.py
netman/adapters/switches/juniper/base.py
netman/adapters/switches/juniper/mx.py
netman/adapters/switches/juniper/qfx_copper.py
netman/adapters/switches/juniper/standard.py
netman/api/__init__.py
netman/api/api_utils.py
netman/api/netman_api.py
netman/api/switch_api.py
netman/api/switch_api_base.py
netman/api/switch_session_api.py
netman/api/validators.py
netman/api/doc_config/Makefile
netman/api/doc_config/conf.py
netman/api/doc_config/index.rst
netman/api/doc_config/api_samples/get_info.json
netman/api/doc_config/api_samples/get_switch_hostname_bond_v1.json
netman/api/doc_config/api_samples/get_switch_hostname_bond_v2.json
netman/api/doc_config/api_samples/get_switch_hostname_bonds_v1.json
netman/api/doc_config/api_samples/get_switch_hostname_bonds_v2.json
netman/api/doc_config/api_samples/get_switch_hostname_interface.json
netman/api/doc_config/api_samples/get_switch_hostname_interfaces.json
netman/api/doc_config/api_samples/get_switch_hostname_mac_addresses.json
netman/api/doc_config/api_samples/get_switch_hostname_versions.json
netman/api/doc_config/api_samples/get_switch_hostname_vlans.json
netman/api/doc_config/api_samples/get_switch_hostname_vlans_vlan.json
netman/api/doc_config/api_samples/get_switch_hostname_vlans_vlan_interfaces.json
netman/api/doc_config/api_samples/post_switch_hostname_bonds.json
netman-1.5.1.dist-info/AUTHORS
netman-1.5.1.dist-info/LICENSE
netman-1.5.1.dist-info/METADATA
netman-1.5.1.dist-info/WHEEL
netman-1.5.1.dist-info/pbr.json
netman-1.5.1.dist-info/top_level.txt
netman-1.5.1.dist-info/RECORD
