Metadata-Version: 2.1
Name: netman
Version: 1.5.1
Summary: A unified REST API to provide vendor-agnostic network automation
Home-page: https://github.com/internaphosting/netman
Author: Internap Hosting
Author-email: opensource@internap.com
License: UNKNOWN
Platform: UNKNOWN
Classifier: Development Status :: 5 - Production/Stable
Classifier: Intended Audience :: Developers
Classifier: Intended Audience :: Information Technology
Classifier: Intended Audience :: System Administrators
Classifier: Intended Audience :: Telecommunications Industry
Classifier: License :: OSI Approved :: Apache Software License
Classifier: Operating System :: POSIX
Classifier: Programming Language :: Python :: 2.7
Requires-Dist: pbr (>=1.8)
Requires-Dist: Flask (>=0.11)
Requires-Dist: paramiko (>=1.15.1)
Requires-Dist: netaddr (>=0.7.13)
Requires-Dist: ncclient (>=0.5.0)
Requires-Dist: requests (>=2.6.2)
Requires-Dist: pyeapi
